litespeed/__init__.py
litespeed/error.py
litespeed/helpers.py
litespeed/mail.py
litespeed/server.py
litespeed/utils.py
litespeed/html/500.html
LiteSpeed-1.2.0.dist-info/LICENSE.md
LiteSpeed-1.2.0.dist-info/METADATA
LiteSpeed-1.2.0.dist-info/WHEEL
LiteSpeed-1.2.0.dist-info/top_level.txt
LiteSpeed-1.2.0.dist-info/RECORD
